mt/struct/__init__.pxd
mt/struct/__init__.py
mt/struct/trie.cpp
mt/struct/trie.cpython-38-x86_64-linux-gnu.so
mt/struct/trie.pxd
mt/struct/trie.pyx
mt/struct/version.py
mtstruct-0.2.1.dist-info/METADATA
mtstruct-0.2.1.dist-info/WHEEL
mtstruct-0.2.1.dist-info/top_level.txt
mtstruct-0.2.1.dist-info/RECORD
